python_repeatable_iterable/__init__.py
python_repeatable_iterable/py.typed
python_repeatable_iterable-2.1.8.dist-info/METADATA
python_repeatable_iterable-2.1.8.dist-info/WHEEL
python_repeatable_iterable-2.1.8.dist-info/licenses/COPYING
python_repeatable_iterable-2.1.8.dist-info/licenses/COPYING.LESSER
python_repeatable_iterable-2.1.8.dist-info/RECORD
